LICENSE
README.md
setup.py
tests/__init__.py
tests/helper.py
tests/test_audit.py
tests/test_effects.py
tests/test_exceptions.py
tests/test_parser.py
tests/test_policy.py
tests/test_util.py
tests/test_version.py
tests/cache/__init__.py
tests/cache/test_allowance_cache.py
tests/cache/test_enfold_cache.py
tests/storage/__init__.py
tests/storage/test_abc.py
tests/storage/test_memory.py
tests/storage/test_migration.py
tests/storage/test_mongo.py
tests/storage/test_mongo_migration.py
tests/storage/test_observable.py
tests/storage/test_redis.py
tests/storage/sql/__init__.py
tests/storage/sql/test_migrations.py
tests/storage/sql/test_model.py
tests/storage/sql/test_sql.py
vakt/__init__.py
vakt/audit.py
vakt/cache.py
vakt/checker.py
vakt/effects.py
vakt/exceptions.py
vakt/guard.py
vakt/parser.py
vakt/policy.py
vakt/util.py
vakt/version.py
vakt.egg-info/PKG-INFO
vakt.egg-info/SOURCES.txt
vakt.egg-info/dependency_links.txt
vakt.egg-info/requires.txt
vakt.egg-info/top_level.txt
vakt/rules/__init__.py
vakt/rules/base.py
vakt/rules/inquiry.py
vakt/rules/list.py
vakt/rules/logic.py
vakt/rules/net.py
vakt/rules/operator.py
vakt/rules/string.py
vakt/storage/__init__.py
vakt/storage/abc.py
vakt/storage/memory.py
vakt/storage/migration.py
vakt/storage/mongo.py
vakt/storage/observable.py
vakt/storage/redis.py
vakt/storage/sql/__init__.py
vakt/storage/sql/migrations.py
vakt/storage/sql/model.py