Metadata-Version: 2.1
Name: vakt
Version: 1.6.0
Summary: Attribute-based access control (ABAC) SDK for Python
Home-page: http://github.com/kolotaev/vakt
Author: Egor Kolotaev
Author-email: ekolotaev@gmail.com
License: Apache 2.0 license
Keywords: ACL ABAC access-control policy security authorization permission
Classifier: Intended Audience :: Developers
Classifier: License :: OSI Approved :: Apache Software License
Classifier: Operating System :: OS Independent
Classifier: Topic :: System :: Systems Administration
Classifier: Topic :: System :: Networking
Classifier: Topic :: System :: Networking :: Firewalls
Classifier: Topic :: Security
Classifier: Topic :: Software Development
Classifier: Topic :: Utilities
Classifier: Natural Language :: English
Classifier: Programming Language :: Python
Classifier: Programming Language :: Python :: 3
Classifier: Programming Language :: Python :: 3.6
Classifier: Programming Language :: Python :: 3.7
Classifier: Programming Language :: Python :: 3.8
Classifier: Programming Language :: Python :: 3.9
Classifier: Programming Language :: Python :: 3.10
Classifier: Programming Language :: Python :: 3.11
Classifier: Programming Language :: Python :: Implementation :: CPython
Classifier: Programming Language :: Python :: Implementation :: PyPy
Requires-Python: >=3.6
Provides-Extra: dev
Provides-Extra: mongo
Provides-Extra: sql
Provides-Extra: redis
License-File: LICENSE
